CHANGELOG
LICENSE
MANIFEST.in
README.rst
extras_requirements.txt
requirements.txt
setup.py
hippybot/__init__.py
hippybot/bot.py
hippybot/decorators.py
hippybot/hipchat.py
hippybot/version.txt
hippybot.egg-info/PKG-INFO
hippybot.egg-info/SOURCES.txt
hippybot.egg-info/dependency_links.txt
hippybot.egg-info/entry_points.txt
hippybot.egg-info/requires.txt
hippybot.egg-info/top_level.txt
hippybot/daemon/__init__.py
hippybot/daemon/daemon.py
hippybot/plugins/__init__.py
hippybot/plugins/hype.py
hippybot/plugins/lockbot.py
hippybot/plugins/plusplusbot.py
hippybot/plugins/rot13.py
hippybot/plugins/threaded_example.py
hippybot/plugins/udefine.py
hippybot/plugins/uptime.py
hippybot/plugins/wave.py