Metadata-Version: 1.0
Name: hippybot
Version: 1.2.7
Summary: Python Hipchat bot
Home-page: http://github.com/1stvamp/hippybot
Author: Wes Mason
Author-email: wes[at]1stvamp[dot]org
License: BSD
Platform: UNKNOWN
